bobros/__init__.py
bobros/main.py
bobros-0.2.0.dist-info/entry_points.txt
bobros-0.2.0.dist-info/WHEEL
bobros-0.2.0.dist-info/METADATA
bobros-0.2.0.dist-info/RECORD
