Metadata-Version: 2.1
Name: bobros
Version: 0.2.0
Summary: A tool to set file and folder colours in Idea projects
Author: Timofey Danshin
Author-email: t.danshin@gmail.com
Requires-Python: >=3.6,<4.0
Classifier: Programming Language :: Python :: 3
Classifier: Programming Language :: Python :: 3.6
Classifier: Programming Language :: Python :: 3.7
Classifier: Programming Language :: Python :: 3.8
Classifier: Programming Language :: Python :: 3.9
Requires-Dist: PyYAML (>=5.3.1,<6.0.0)
Requires-Dist: click (>=7.1.2,<8.0.0)
Requires-Dist: colour (>=0.1.5,<0.2.0)
Requires-Dist: ruamel.yaml (>=0.16.12,<0.17.0)
